README.rst
setup.py
contexttimer/__init__.py
contexttimer/timeout.py
contexttimer.egg-info/PKG-INFO
contexttimer.egg-info/SOURCES.txt
contexttimer.egg-info/dependency_links.txt
contexttimer.egg-info/top_level.txt