Metadata-Version: 1.1
Name: contexttimer
Version: 0.3.0
Summary: A timer context manager measuring the clock wall time of the code block it contains.
Home-page: https://github.com/brouberol/contexttimer
Author: Balthazar Rouberol
Author-email: brouberol@imap.cc
License: GPLv3
Keywords: time,timer
Platform: UNKNOWN
Classifier: Intended Audience :: Developers
Classifier: License :: OSI Approved :: GNU General Public License v3 (GPLv3)
Classifier: Operating System :: OS Independent
Classifier: Programming Language :: Python :: 2
Classifier: Programming Language :: Python :: 3
Classifier: Topic :: Utilities
